{
    "CouchbaseSyncGateway": {
        "ap-northeast-1": {
            "AMI": "ami-098b61e872ec9c4a5"
        },
        "ap-northeast-2": {
            "AMI": "ami-05d81037e9e7e3469"
        },
        "ap-south-1": {
            "AMI": "ami-0d05c40dd35dbab22"
        },
        "ap-southeast-1": {
            "AMI": "ami-0ffbe780887a527be"
        },
        "ap-southeast-2": {
            "AMI": "ami-0d0aef0188c3500ee"
        },
        "ca-central-1": {
            "AMI": "ami-0bcf614070b977409"
        },
        "eu-central-1": {
            "AMI": "ami-00a912a9071f8c8c2"
        },
        "eu-west-1": {
            "AMI": "ami-0affd91c45636a91f"
        },
        "eu-west-2": {
            "AMI": "ami-0f2fbd753144bed78"
        },
        "eu-west-3": {
            "AMI": "ami-00d3a2fc678c3193e"
        },
        "sa-east-1": {
            "AMI": "ami-092a972aa8afe2982"
        },
        "us-east-1": {
            "AMI": "ami-07c3349c35f179498"
        },
        "us-east-2": {
            "AMI": "ami-038c73d98d4cd654d"
        },
        "us-west-1": {
            "AMI": "ami-07ec4dae6e4f68ac2"
        },
        "us-west-2": {
            "AMI": "ami-04f61679f6fc9eee9"
        }
    }
}
